LICENSE.txt
MANIFEST.in
README.rst
requirements.txt
setup.cfg
setup.py
doc/Makefile
doc/conf.py
doc/index.rst
doc/objects.inv
doc/security.1
doc/rst/install.rst
doc/rst/module.rst
doc/rst/refman.rst
doc/rst/tutor.rst
doc/rst/install/extensions.rst
doc/rst/install/ext/security.rst
doc/rst/module/extensions.rst
doc/rst/module/ext/security/main.rst
doc/rst/module/ext/security/msf.rst
doc/rst/module/ext/security/security.rst
doc/rst/module/ext/security/zap.rst
doc/rst/refman/ext/security.rst
doc/rst/tutor/extensions.rst
doc/rst/tutor/ext/security/msf.rst
doc/rst/tutor/ext/security/security.rst
doc/rst/tutor/ext/security/zap.rst
etc/hydratk/conf.d/hydratk-ext-security.conf
src/hydratk/__init__.py
src/hydratk/extensions/__init__.py
src/hydratk/extensions/security/__init__.py
src/hydratk/extensions/security/bootstrapper.py
src/hydratk/extensions/security/msf.py
src/hydratk/extensions/security/msf_api.py
src/hydratk/extensions/security/security.py
src/hydratk/extensions/security/zap.py
src/hydratk/extensions/security/translation/__init__.py
src/hydratk/extensions/security/translation/info.py
src/hydratk/extensions/security/translation/cs/__init__.py
src/hydratk/extensions/security/translation/cs/help.py
src/hydratk/extensions/security/translation/cs/messages.py
src/hydratk/extensions/security/translation/en/__init__.py
src/hydratk/extensions/security/translation/en/help.py
src/hydratk/extensions/security/translation/en/messages.py
src/hydratk_ext_security.egg-info/PKG-INFO
src/hydratk_ext_security.egg-info/SOURCES.txt
src/hydratk_ext_security.egg-info/dependency_links.txt
src/hydratk_ext_security.egg-info/entry_points.txt
src/hydratk_ext_security.egg-info/not-zip-safe
src/hydratk_ext_security.egg-info/top_level.txt
tests/travis.yoda
tests/yoda-tests/hydratk/extensions/security/bootstrapper/01_methods_ut.jedi
tests/yoda-tests/hydratk/extensions/security/msf/01_methods_ut.jedi
tests/yoda-tests/hydratk/extensions/security/security/01_methods_ut.jedi
tests/yoda-tests/hydratk/extensions/security/zap/01_methods_ut.jedi
tests/yodahelpers/hydratk/extensions/security/__init__.py
tests/yodalib/hydratk/extensions/security/__init__.py